anime2you/__init__.py
anime2you/feed.py
anime2you/rss_manager.py
Anime2You-1.0.0.dist-info/LICENSE
Anime2You-1.0.0.dist-info/METADATA
Anime2You-1.0.0.dist-info/WHEEL
Anime2You-1.0.0.dist-info/top_level.txt
Anime2You-1.0.0.dist-info/RECORD
