Metadata-Version: 2.1
Name: Anime2You
Version: 1.0.0
Summary: Unofficial RSSClient for Anime2You
Home-page: https://github.com/princessmiku/anime2you
Author: Miku
Author-email: 
License: MIT
Keywords: anime2you,rss,news,anime,rssclient,german
Classifier: Programming Language :: Python :: 3.7
Classifier: Programming Language :: Python :: 3.8
Classifier: Programming Language :: Python :: 3.9
Classifier: Programming Language :: Python :: 3.10
Classifier: Programming Language :: Python :: 3.11
Classifier: Programming Language :: Python :: 3.12
Requires-Python: >=3.7.0
License-File: LICENSE
Requires-Dist: feedparser >=6.0.11
